sv_ttk_colorizer/__init__.py
sv_ttk_colorizer/__main__.py
sv_ttk_colorizer/assistance.py
sv_ttk_colorizer/util.py
sv_ttk_colorizer/resources/LICENSE_MODIFICATIONS
sv_ttk_colorizer/resources/example.py
sv_ttk_colorizer/resources/image.png
sv_ttk_colorizer/resources/dark/preview.png
sv_ttk_colorizer/resources/dark/preview_accent.png
sv_ttk_colorizer/resources/dark/preview_accent_text.png
sv_ttk_colorizer/resources/hue_scale/thumb_dark.png
sv_ttk_colorizer/resources/hue_scale/thumb_disabled_dark.png
sv_ttk_colorizer/resources/hue_scale/thumb_disabled_light.png
sv_ttk_colorizer/resources/hue_scale/thumb_hover_dark.png
sv_ttk_colorizer/resources/hue_scale/thumb_hover_light.png
sv_ttk_colorizer/resources/hue_scale/thumb_light.png
sv_ttk_colorizer/resources/hue_scale/thumb_pressed_dark.png
sv_ttk_colorizer/resources/hue_scale/thumb_pressed_light.png
sv_ttk_colorizer/resources/hue_scale/track.png
sv_ttk_colorizer/resources/icon/16x16.png
sv_ttk_colorizer/resources/icon/32x32.png
sv_ttk_colorizer/resources/icon/48x48.png
sv_ttk_colorizer/resources/light/preview.png
sv_ttk_colorizer/resources/light/preview_accent.png
sv_ttk_colorizer/resources/light/preview_accent_text.png
sv_ttk_colorizer/resources/theme_switcher/bg_dark.png
sv_ttk_colorizer/resources/theme_switcher/bg_light.png
sv_ttk_colorizer-1.3.2.dist-info/LICENSE
sv_ttk_colorizer-1.3.2.dist-info/METADATA
sv_ttk_colorizer-1.3.2.dist-info/WHEEL
sv_ttk_colorizer-1.3.2.dist-info/entry_points.txt
sv_ttk_colorizer-1.3.2.dist-info/top_level.txt
sv_ttk_colorizer-1.3.2.dist-info/RECORD
