Metadata-Version: 2.1
Name: sv-ttk-colorizer
Version: 1.3.2
Summary: A module for changing the accent color of @rdbende's Sun Valley ttk theme.
Home-page: https://github.com/Valer100/Sun-Valley-Theme-Colorizer
Author: Valer100
License: MIT
Project-URL: Source, https://github.com/Valer100/Sun-Valley-Theme-Colorizer
Project-URL: Issues, https://github.com/Valer100/Sun-Valley-Theme-Colorizer/issues
Keywords: sv-ttk,sv-ttk-colorizer,sv-ttk-c,sv_ttk_colorizer,sv_ttk_c,theme,tk,ttk,tkinter,modern,fluent,dark-theme,sun-valley,windows-11,winui
Classifier: Intended Audience :: Developers
Classifier: Topic :: Software Development :: User Interfaces
Classifier: Programming Language :: Python :: 3 :: Only
Classifier: License :: OSI Approved :: MIT License
Classifier: Operating System :: OS Independent
Requires-Python: >=3.8
License-File: LICENSE
Requires-Dist: darkdetect
Requires-Dist: Pillow
Requires-Dist: requests
Requires-Dist: pywinstyles
Requires-Dist: sv-ttk
Requires-Dist: appdirs
Requires-Dist: tkscrollframe
